revoize/__init__.py
revoize/api/__init__.py
revoize/api/client.py
revoize/api/exceptions.py
revoize/api/utils.py
revoize/cli/enhance.py
revoize/defaults.py
revoize/schema/__init__.py
revoize/schema/schema.py
revoize-0.3.0.dist-info/LICENSE
revoize-0.3.0.dist-info/METADATA
revoize-0.3.0.dist-info/WHEEL
revoize-0.3.0.dist-info/entry_points.txt
revoize-0.3.0.dist-info/RECORD
